darkest/__init__.py
darkest/__main__.py
darkest/format.py
darkest/version.py
darkest-0.5.0.dist-info/licenses/LICENSE
darkest-0.5.0.dist-info/METADATA
darkest-0.5.0.dist-info/WHEEL
darkest-0.5.0.dist-info/entry_points.txt
darkest-0.5.0.dist-info/top_level.txt
darkest-0.5.0.dist-info/RECORD
